README.rst
setup.py
./__init__.py
./app.py
./asynchronous.py
./mock_result.py
./serialization.py
./tasks.py
./tryton.cfg
./tests/__init__.py
./tests/test_async.py
./tests/test_serialization.py
fio_async.egg-info/PKG-INFO
fio_async.egg-info/SOURCES.txt
fio_async.egg-info/dependency_links.txt
fio_async.egg-info/entry_points.txt
fio_async.egg-info/not-zip-safe
fio_async.egg-info/requires.txt
fio_async.egg-info/top_level.txt